rldeploy/rl-deploy.exe
rldeploy/libcrypto-3.dll
rldeploy/libssl-3.dll
rldeploy/__init__.py
rldeploy/__main__.py
rl_deploy-2.4.8.0.dist-info/entry_points.txt
rl_deploy-2.4.8.0.dist-info/WHEEL
rl_deploy-2.4.8.0.dist-info/METADATA
rl_deploy-2.4.8.0.dist-info/RECORD