Metadata-Version: 2.1
Name: rl-deploy
Version: 2.4.8.0
Summary: Deployment tool for ReversingLabs rl-secure project.
Author: ReversingLabs
Author-email: secure.software@reversinglabs.com
Requires-Python: >=2.7
Classifier: Development Status :: 5 - Production/Stable
Classifier: Intended Audience :: Developers
Classifier: Natural Language :: English
Classifier: Topic :: Security
